Workbook

Sheet Resumen
C4: Años | D4: 0 | E4: 1 | F4: 2 | G4: 3 | H4: 4 | I4: 5 | J4: TOTAL
C5: Windows | D5: =Windows!E13 -> 104163.86 | E5: =Windows!F13 -> 2100 | F5: =Windows!G13 -> 2100 | G5: =Windows!H13 -> 2100 | H5: =Windows!I13 -> 2100 | I5: =Windows!J13 -> 2100 | J5: =SUM(D5:I5) -> 114663.86
C6: Linux | D6: =Linux!E13 -> 94415.86 | E6: =Linux!F13 -> 2700 | F6: =Linux!G13 -> 2700 | G6: =Linux!H13 -> 2700 | H6: =Linux!I13 -> 2700 | I6: =Linux!J13 -> 2700 | J6: =SUM(D6:I6) -> 107915.86
C7: Chromebooks | D7: =Chromebooks!D13 -> 28482 | E7: =Chromebooks!E13 -> 4942 | F7: =Chromebooks!F13 -> 3300 | G7: =Chromebooks!G13 -> 3320 | H7: =Chromebooks!H13 -> 3320 | I7: =Chromebooks!I13 -> 3320 | J7: =SUM(D7:I7) -> 46684
M10: Hardware acquisition | N10: Purchase price of computer hardware equipment, including computers, terminals, storage, and printers
C11: Se utiliza un interes del | E11: 0.03 | M11: Software acquisition | N11: Purchase or license of software for each user
M12: Installation | N12: Cost to install computers and software
C13: Años | D13: 0 | E13: 1 | F13: 2 | G13: 3 | H13: 4 | I13: 5 | M13: Training | N13: Cost to provide training for information systems specialists and end users
C14: Incremento | D14: =(1+$E$11)^D13 -> 1 | E14: =(1+$E$11)^E13 -> 1.03 | F14: =(1+$E$11)^F13 -> 1.0609 | G14: =(1+$E$11)^G13 -> 1.092727 | H14: =(1+$E$11)^H13 -> 1.1255088 | I14: =(1+$E$11)^I13 -> 1.1592741 | M14: Support | N14: Cost to provide ongoing technical support, help desks, and so forth
M15: Maintenance | N15: Cost to upgrade the hardware and software
M16: Infrastructure | N16: Cost to acquire, maintain, and support related infrastructure, such as networks and specialized equipment (including storage backup units)
M17: Downtime | N17: Cost of lost productivity if hardware or software failures cause the system to be unavailable for processing and user tasks
C18: Años | D18: 0 | E18: 1 | F18: 2 | G18: 3 | H18: 4 | I18: 5 | J18: TOTAL | M18: Space and energy | N18: Real estate and utility costs for housing and providing power for the technology
C19: Windows | D19: =D5/D$14 -> 104163.86 | E19: =E5/E14 -> 2038.835 | F19: =F5/F14 -> 1979.4514 | G19: =G5/G14 -> 1921.7975 | H19: =H5/H14 -> 1865.8228 | I19: =I5/I14 -> 1811.4784 | J19: =SUM(D19:I19) -> 113781.25
C20: Linux | D20: =D6/D$14 -> 94415.86 | E20: =E6/E$14 -> 2621.3592 | F20: =F6/F$14 -> 2545.009 | G20: =G6/G$14 -> 2470.8825 | H20: =H6/H$14 -> 2398.915 | I20: =I6/I$14 -> 2329.0437 | J20: =SUM(D20:I20) -> 106781.07
C21: Chromebooks | D21: =D7/D$14 -> 28482 | E21: =E7/E$14 -> 4798.0583 | F21: =F7/F$14 -> 3110.5665 | G21: =G7/G$14 -> 3038.2703 | H21: =H7/H$14 -> 2949.777 | I21: =I7/I$14 -> 2863.8612 | J21: =SUM(D21:I21) -> 45242.533
C25: Decision FINAL | D25: Linux
C26: ¿Porque hemos elegido el Linux?
C27: Hemos elegido el Linux porque es mas asequible que el linux. Tambien hemos elegido el Linux porque el mejor Chromebook que hay en el mercado no sirve para cursar varias carreras de la Politecnica, las cuales requieren equipos potentes como la carrera de ingenieria informática que requiere un equipo con mucha RAM para abrir muchas maquinas (Hay varias asignaturas que requieren abrir mas de 4 maquinas para crear con linux y windows equipos que simulen Routers, Switchs y pcs), o como por ejemplo la carrera de arquitectura la cuál requiere equipos potentes en graficos para simular los planos de las estructuras. Entonces un equipo minimo para que puedan desarrollarse todas las carreras con todas las asignaturas de la Politecnica seria el de Windows o el de Linux. Y por lo tanto, hemos elegido ahorrar unos € con la licencia de Windows y hemos elegido Linux como nuestra opcion ideal.

Sheet Windows
D2: Año
C3: INFRAESTRUCTURE COMPONENT | E3: 0 | F3: 1 | G3: 2 | H3: 3 | I3: 4 | J3: 5 | K3: TOTAL
C4: Hardware acquisition | E4: =50*S17 -> 79950 | K4: =SUM(E4:J4) -> 79950
C5: Software acquisition | E5: =50*S18 -> 12680 | K5: =SUM(E5:J5) -> 12680
C6: Installation | E6: =S19*50 -> 600 | K6: =SUM(E6:J6) -> 600
C7: Training | K7: =SUM(E7:J7) -> 0
C8: Support | F8: =50*$S$21 -> 1000 | G8: =50*$S$21 -> 1000 | H8: =50*$S$21 -> 1000 | I8: =50*$S$21 -> 1000 | J8: =50*$S$21 -> 1000 | K8: =SUM(E8:J8) -> 5000
C9: Maintenance | E9: =S22*50 -> 9600 | K9: =SUM(E9:J9) -> 9600
C10: Infrastructure | E10: =S23 -> 1333.86 | K10: =SUM(E10:J10) -> 1333.86
C11: Downtime | F11: =12*50*$S$24 -> 600 | G11: =12*50*$S$24 -> 600 | H11: =12*50*$S$24 -> 600 | I11: =12*50*$S$24 -> 600 | J11: =12*50*$S$24 -> 600 | K11: =12*50*$S$24 -> 600
C12: Space and energy | F12: =10*50 -> 500 | G12: =10*50 -> 500 | H12: =10*50 -> 500 | I12: =10*50 -> 500 | J12: =10*50 -> 500 | K12: =SUM(E12:J12) -> 2500
C13: TOTAL ANUAL | E13: =SUM(E4:E12) -> 104163.86 | F13: =SUM(F4:F12) -> 2100 | G13: =SUM(G4:G12) -> 2100 | H13: =SUM(H4:H12) -> 2100 | I13: =SUM(I4:I12) -> 2100 | J13: =SUM(J4:J12) -> 2100 | K13: =SUM(K4:K12) -> 112263.86
C16: Component | S16: Precio
C17: Hardware | D17: El hardware necesario para que haya varias maquinas virtualizadas (Necesitara al menos 4GB de RAM por equipo virtualizado y suelen haber 4 como minimo por lo tanto 16GB de RAM pero el equipo principal necesita RAM tambien y siempre debe ser el doble al gastado (Si gastas 4GB en abrir programas, el Sistema operativo necesitara 4GB tambien para seguir funcionando correctamente) por lo tanto un equipo ideal sera como minimo 32GB de RAM) necesarias para muchas asignaturas de Informática y el hardware necesario para ejercicios graficos para arquitectura. Hemos elegido el siguiente equipo que da suficientes recursos para poder correr todo sin perder tiempo y que pueda funcionar todo correctamente según los softwares extremos que necesitan algunas carreras. El ordenador portatil sera el siguiente: Portátil ASUS TUF Gaming F16 FX608JPR-QT002 Intel Core i7-14650HX/32GB/1TB SSD/RTX 5070/16" (https://www.pccomponentes.com/portatil-asus-tuf-gaming-f16-fx608jpr-qt002-intel-core-i7-14650hx-32gb-1tb-ssd-rtx-5070-16) | S17: 1599
C18: Software | D18: El equipo no viene instalado el Windows 11 Pro lo adquirimos por un precio 194,96€ por portatil, el Office asi que le instalaremos el office 2019 por 58,64€ por licencia para uso de vida del portatil (Basicamente para siempre, solo para ese equipo) (https://es.gvgmall.com/key/201810041728402402.html) (Asi que 50 licencias para 50 equipos (1 por equipo) son 2932€ y solo un unico pago hasta que cambiemos los equipos de nuevo) , despues cada alumno que use el equipo instalara el software que necesite como el VirtualBox para hacer maquinas virtuales, o el Matlab para calculos. (Tambien se podria ahorrar la licencia de Office 2019 e instalar OpenOffice que es gratuita solo tendrian que pagar el coste de instalación en una empresa externa) | S18: =194.96+58.64 -> 253.6
C19: Instalación | D19: El coste por instalación del sotfware lo realizará el equipo informático de la UBU, si hubiera problemas lo realizará el soporte ya contratado. | S19: 12
C20: Formación | D20: Al ser equipos windows, consideramos a los alumnos suficientemente forrmados.
C21: Soporte | D21: Los fallos generales serán atendidos por el soporte informático de la UBU, el resto de falloso fuera de hora los atenderá una empresa externa. | S21: 20
C22: Mantenimiento | D22: El mantenimineto, que implica mas al HW, lo consideramos como extensión de garantia por 192€ por portatil para 5 años de garantia. | S22: 192
C23: Infraestructura | D23: Carrito - Armario para almacenar portátiles (Necesitamos dos) (https://www.pccomponentes.com/ewent-ew1700-carrito-y-armario-de-dispositivo-portatil-negro?campaigntype=eshopping&campaignchannel=shopping&gad_source=1&gad_campaignid=12885548290&gclid=Cj0KCQjw267GBhCSARIsAOjVJ4FZM0zZpim2Dc4VGRvllj-T4iTWyMp90SOyMyAE89VGOseO-GLT3AkaAi24EALw_wcB) | S23: 1333.86
C24: T. Inactividad | D24: Consideramos 1 hora por equipo al mes, ya que un equipo Windows es mas facil de manejar al usuario y sugiere menos problemas | S24: 1
C25: Espacio y Energia | D25: Consideramos de el coste de energia 10€ mensuales | S25: 10

Sheet Linux
D2: Año
C3: INFRAESTRUCTURE COMPONENT | E3: 0 | F3: 1 | G3: 2 | H3: 3 | I3: 4 | J3: 5 | K3: TOTAL
C4: Hardware acquisition | E4: =50*S17 -> 79950 | K4: =SUM(E4:J4) -> 79950
C5: Software acquisition | E5: =50*S18 -> 2932 | K5: =SUM(E5:J5) -> 2932
C6: Installation | E6: =50*S19 -> 600 | K6: =SUM(E6:J6) -> 600
C7: Training | K7: =SUM(E7:J7) -> 0
C8: Support | F8: =50*$S$21 -> 1000 | G8: =50*$S$21 -> 1000 | H8: =50*$S$21 -> 1000 | I8: =50*$S$21 -> 1000 | J8: =50*$S$21 -> 1000 | K8: =SUM(E8:J8) -> 5000
C9: Maintenance | E9: =S22*50 -> 9600 | K9: =SUM(E9:J9) -> 9600
C10: Infrastructure | E10: =S23 -> 1333.86 | K10: =SUM(E10:J10) -> 1333.86
C11: Downtime | F11: =12*50*$S$24 -> 1200 | G11: =12*50*$S$24 -> 1200 | H11: =12*50*$S$24 -> 1200 | I11: =12*50*$S$24 -> 1200 | J11: =12*50*$S$24 -> 1200 | K11: =12*50*$S$24 -> 1200
C12: Space and energy | F12: =10*50 -> 500 | G12: =10*50 -> 500 | H12: =10*50 -> 500 | I12: =10*50 -> 500 | J12: =10*50 -> 500 | K12: =SUM(E12:J12) -> 2500
C13: TOTAL ANUAL | E13: =SUM(E4:E12) -> 94415.86 | F13: =SUM(F4:F12) -> 2700 | G13: =SUM(G4:G12) -> 2700 | H13: =SUM(H4:H12) -> 2700 | I13: =SUM(I4:I12) -> 2700 | J13: =SUM(J4:J12) -> 2700 | K13: =SUM(K4:K12) -> 103115.86
C16: COMPONENT | S16: Precio
C17: Hardware | D17: El hardware necesario para que haya varias maquinas virtualizadas (Necesitara al menos 4GB de RAM por equipo virtualizado y suelen haber 4 como minimo por lo tanto 16GB de RAM pero el equipo principal necesita RAM tambien y siempre debe ser el doble al gastado (Si gastas 4GB en abrir programas, el Sistema operativo necesitara 4GB tambien para seguir funcionando correctamente) por lo tanto un equipo ideal sera como minimo 32GB de RAM) necesarias para muchas asignaturas de Informática y el hardware necesario para ejercicios graficos para arquitectura. Hemos elegido el siguiente equipo que da suficientes recursos para poder correr todo sin perder tiempo y que pueda funcionar todo correctamente según los softwares extremos que necesitan algunas carreras. El ordenador portatil sera el siguiente: Portátil ASUS TUF Gaming F16 FX608JPR-QT002 Intel Core i7-14650HX/32GB/1TB SSD/RTX 5070/16" (https://www.pccomponentes.com/portatil-asus-tuf-gaming-f16-fx608jpr-qt002-intel-core-i7-14650hx-32gb-1tb-ssd-rtx-5070-16) | S17: 1599
C18: Software | D18: Licencia de Office 2019 por 58,64€ para uso de vida del portatil (Basicamente para siempre, solo para ese equipo) (https://es.gvgmall.com/key/201810041728402402.html) . Despues cada alumno que use el equipo instalara el software que necesite como el VirtualBox para hacer maquinas virtuales, o el Matlab para calculos. (Tambien se podria ahorrar la licencia de Office 2019 e instalar OpenOffice que es gratuita solo tendrian que pagar el coste de instalación en una empresa externa) | S18: 58.64
C19: Instalación | D19: El coste por instalación del sotfware lo hemos puesto a 12€ por equipo como decimos en la sección software, y el coste por montaje del equipo ya esta incluido en el precio del hardware. | S19: 12
C20: Formación | D20: Los alumnos pueden no tener formación en Linux. Necesitaran formación. Para ello hemos encontrado un curso gratuito para la formación de Linux: https://edutin.com/curso-de-linux
C21: Soporte | D21: Los fallos generales serán atendidos por el soporte informático de la UBU, el resto de fallos fuera de hora los atenderá una empresa externa. | S21: 20
C22: Mantenimiento | D22: El mantenimineto, que implica mas al HW, lo consideramos como extensión de garantia por 192€ por portatil para 5 años de garantia. | S22: 192
C23: Infraestructura | D23: Carrito - Armario para almacenar portátiles (Necesitamos dos) (https://www.pccomponentes.com/ewent-ew1700-carrito-y-armario-de-dispositivo-portatil-negro?campaigntype=eshopping&campaignchannel=shopping&gad_source=1&gad_campaignid=12885548290&gclid=Cj0KCQjw267GBhCSARIsAOjVJ4FZM0zZpim2Dc4VGRvllj-T4iTWyMp90SOyMyAE89VGOseO-GLT3AkaAi24EALw_wcB) | S23: 1333.86
C24: T. Inactividad | D24: Consideramos 2 horas por equipo al mes | S24: 2
C25: Espacio y Energia | D25: Consideramos de el coste de energia 10€ mensuales por equipo | S25: 10

Sheet Chromebooks
C2: AÑO
B3: INFRAESTRUCTURE COMPONENT | D3: 0 | E3: 1 | F3: 2 | G3: 3 | H3: 4 | I3: 5 | J3: TOTAL
B4: Hardware acquisition | D4: =R19*50 -> 24950 | J4: =SUM(D4:I4) -> 24950
B5: Software acquisition | D5: =R20*50 -> 2932 | J5: =SUM(D5:I5) -> 2932
B6: Installation | D6: =50*R21 -> 600 | J6: =SUM(D6:I6) -> 600
B7: Training | J7: =SUM(D7:I7) -> 0
B8: Support | E8: =50*$R$23 -> 1000 | F8: =50*$R$23 -> 1000 | G8: =50*$R$23 -> 1000 | H8: =50*$R$23 -> 1000 | I8: =50*$R$23 -> 1000 | J8: =SUM(D8:I8) -> 5000
B9: Maintenance | G9: =$R$24 -> 20 | H9: =$R$24 -> 20 | I9: =$R$24 -> 20 | J9: =SUM(D9:I9) -> 60
B10: Infrastructure | E10: 1642 | J10: =SUM(D10:I10) -> 1642
B11: Downtime | E11: =12*50*$R$26 -> 1800 | F11: =12*50*$R$26 -> 1800 | G11: =12*50*$R$26 -> 1800 | H11: =12*50*$R$26 -> 1800 | I11: =12*50*$R$26 -> 1800 | J11: =12*50*$R$26 -> 1800
B12: Space and energy | E12: =10*50 -> 500 | F12: =10*50 -> 500 | G12: =10*50 -> 500 | H12: =10*50 -> 500 | I12: =10*50 -> 500 | J12: =SUM(D12:I12) -> 2500
B13: TOTAL ANUAL | D13: =SUM(D4:D12) -> 28482 | E13: =SUM(E4:E12) -> 4942 | F13: =SUM(F4:F12) -> 3300 | G13: =SUM(G4:G12) -> 3320 | H13: =SUM(H4:H12) -> 3320 | I13: =SUM(I4:I12) -> 3320 | J13: =SUM(J4:J12) -> 39484
B17: Google for Education - Recursos online para docentes y alumnos
R18: Precio
B19: Hardware | C19: Portátil ASUS Chromebook Plus CX3402CBA-PQ0692 Intel Core i5-1235U/16GB/256GB UFS/14" | PcComponente | PcComponentes.com | R19: 499
B20: Software | C20: Se instalará OpenOffice, o cualquier distribución ofimatica gratuita. | R20: 58.64
B21: Instalación | C21: El coste por instalación del sotfware ya esta incluido en el precio de las licencias, y el coste por montaje del equipo ya esta incluido en el precio del hardware. | R21: 12
B22: Formación | C22: Los alumnos pueden necesitar algo de formación, menos que en equipos Linux, al ser sistemas mas sencillos.
B23: Soporte | C23: Los fallos generales serán atendidos por el soporte informático de la UBU, el resto de falloso fuera de hora los atenderá una empresa externa. | R23: 20
B24: Mantenimiento | C24: El mantenimineto, que implica mas al HW, lo consideramos como extensión de garantia, a partir del segundo año. | R24: 20
B25: Infraestructura | C25: Carrito - Armario para almacenar portátiles (Necesitamos dos) (https://www.pccomponentes.com/ewent-ew1700-carrito-y-armario-de-dispositivo-portatil-negro?campaigntype=eshopping&campaignchannel=shopping&gad_source=1&gad_campaignid=12885548290&gclid=Cj0KCQjw267GBhCSARIsAOjVJ4FZM0zZpim2Dc4VGRvllj-T4iTWyMp90SOyMyAE89VGOseO-GLT3AkaAi24EALw_wcB) | R25: 1333.86
B26: T. Inactividad | C26: Consideramos 2 horas por equipo al mes, ya qu este equipo necesita conexión a internet para funcionar | R26: 3
B27: Espacio y Energia | C27: Consideramos de el coste de energia 10€ mensuales | R27: 10
