Workbook

Sheet Ventas
A1: IdCliente | B1: NombreCliente | C1: Pais | D1: IdProducto | E1: CanalVentas | F1: UdsVendidas | G1: FechaVenta
A2: 23262 | B2: CESAR VARGAS | C2: Comoros | D2: C1 | E2: Online | F2: 117 | G2: 42591
A3: 23263 | B3: CARLA CABALLERO | C3: Panama | D3: B2 | E3: Online | F3: 73 | G3: 42557
A4: 23264 | B4: MATEO SANCHEZ | C4: Tanzania | D4: B3 | E4: Retail | F4: 205 | G4: 42600
A5: 23265 | B5: ADRIAN GIL | C5: South Africa | D5: C4 | E5: Retail | F5: 14 | G5: 42587
A6: 23266 | B6: CAROLINA FRANCO | C6: Gabon | D6: A2 | E6: Retail | F6: 170 | G6: 42593
A7: 23267 | B7: RAUL AVILA | C7: Syria | D7: A1 | E7: Retail | F7: 129 | G7: 42562
A8: 23268 | B8: ENRIQUE PEREIRA | C8: Grenada | D8: B1 | E8: Online | F8: 82 | G8: 42563
A9: 23269 | B9: ALBERTO LUQUE | C9: Macedonia | D9: A1 | E9: Retail | F9: 116 | G9: 42524
A10: 23270 | B10: ALBERTO MORALES | C10: Kyrgyzstan | D10: C3 | E10: Online | F10: 67 | G10: 42528
A11: 23271 | B11: ADRIAN MARTINEZ | C11: Republic of the Congo | D11: C3 | E11: Retail | F11: 125 | G11: 42578
A12: 23272 | B12: INES MARTINEZ | C12: Turkmenistan | D12: B2 | E12: Retail | F12: 71 | G12: 42582
A13: 23273 | B13: JUDITH RODRIGUEZ | C13: Netherlands | D13: C4 | E13: Online | F13: 22 | G13: 42595
... A999: 24259 | B999: PAOLA RAMIREZ | C999: China | D999: A4 | E999: Online | F999: 138 | G999: 42225

Sheet Productos
A1: IdProducto | B1: productName | C1: CosteStandard | D1: PrecioStandard
A2: A1 | B2: botellín 200cc | C2: 1.5 | D2: 3
A3: A2 | B3: botellín 300cc | C3: 2 | D3: 3.99
A4: A2 | B4: botellín 400cc | C4: 2.3 | D4: 4.5
A5: A4 | B5: botellín 500cc | C5: 3.5 | D5: 6.5
A6: B1 | B6: botella 0.5l | C6: 3 | D6: 6
A7: B2 | B7: botella 1l | C7: 3.5 | D7: 6.5
A8: B3 | B8: botella 5l | C8: 6 | D8: 9
A9: C1 | B9: garrafa 1l | C9: 1 | D9: 2
A10: C2 | B10: garrafa 2l | C10: 2.5 | D10: 4.5
A11: C3 | B11: garrafa 3l | C11: 3.5 | D11: 6.99
A12: C4 | B12: garrafa 4l | C12: 5 | D12: 9.99
A13: C5 | B13: garrafa 8l | C13: 8 | D13: 14.5

Sheet Países
A1: País | B1: Region
A2: Afghanistan | B2: Middle East and North Africa
A3: Albania | B3: Europe
A4: Algeria | B4: Middle East and North Africa
A5: Andorra | B5: Europe
A6: Angola | B6: Sub-Saharan Africa
A7: Antigua and Barbuda | B7: Central America and the Caribbean
A8: Armenia | B8: Europe
A9: Australia | B9: Australia and Oceania
A10: Austria | B10: Europe
A11: Azerbaijan | B11: Middle East and North Africa
A12: Bahrain | B12: Middle East and North Africa
... A186: Zimbabwe | B186: Sub-Saharan Africa

Sheet Clientes
A1: IdCliente | B1: NombreCliente
A2: 23262 | B2: CESAR VARGAS
A3: 23263 | B3: CARLA CABALLERO
A4: 23264 | B4: MATEO SANCHEZ
A5: 23265 | B5: ADRIAN GIL
A6: 23266 | B6: CAROLINA FRANCO
A7: 23267 | B7: RAUL AVILA
A8: 23268 | B8: ENRIQUE PEREIRA
A9: 23269 | B9: ALBERTO LUQUE
A10: 23270 | B10: ALBERTO MORALES
A11: 23271 | B11: ADRIAN MARTINEZ
A12: 23272 | B12: INES MARTINEZ
A13: 23273 | B13: JUDITH RODRIGUEZ
... A999: 24259 | B999: PAOLA RAMIREZ

Sheet Inventarios
B1: InventarioMedio | C1: [euros]
A2: Region | B2: 2015 | C2: 2016
A3: Asia | B3: 10972 | C3: 18721
A4: Australia and Oceania | B4: 4047 | C4: 9654
A5: Central America and the Caribbean | B5: 7690 | C5: 14672
A6: Europe | B6: 12372 | C6: 22716
A7: Middle East and North Africa | B7: 11415 | C7: 15102
A8: North America | B8: 285 | C8: 1429
A9: Sub-Saharan Africa | B9: 26618 | C9: 39447

Sheet Estimaciones
B1: VariaciónVentas del 2017 sobre ventas del 2016
A2: Region | B2: Pesimista | C2: Optimista
A3: Asia | B3: 0.04 | C3: 0.16
A4: Australia and Oceania | B4: 0.01 | C4: 0.03
A5: Central America and the Caribbean | B5: 0.02 | C5: 0.04
A6: Europe | B6: -0.02 | C6: 0.02
A7: Middle East and North Africa | B7: -0.01 | C7: 0.05
A8: North America | B8: 0.02 | C8: 0.04
A9: Sub-Saharan Africa | B9: -0.03 | C9: 0.07

Sheet Calculos
B1: UNIDADES VENDIDAS | C1: INGRESOS | D1: COSTES | E1: BENEFICIOS | F1: AÑO | G1: MES | H1: REGIÓN | I1: CANAL DE VENTAS
B2: =Ventas!F2 -> 117 | C2: =VLOOKUP(Ventas!$D2,Productos!$A$1:$D$16,4,FALSE)*Ventas!F2 -> 234 | D2: =VLOOKUP(Ventas!$D2,Productos!$A$1:$D$16,3,FALSE)*Ventas!F2 -> 117 | E2: =C2-D2 -> 117 | F2: =YEAR(Ventas!G2) -> 2016 | G2: =MONTH(Ventas!G2) -> 8 | H2: =VLOOKUP(Ventas!C2,Países!$A$2:$B$186,2,FALSE) -> Sub-Saharan Africa | I2: =Ventas!E2 -> Online
B3: =Ventas!F3 -> 73 | C3: =VLOOKUP(Ventas!$D3,Productos!$A$1:$D$16,4,FALSE)*Ventas!F3 -> 474.5 | D3: =VLOOKUP(Ventas!$D3,Productos!$A$1:$D$16,3,FALSE)*Ventas!F3 -> 255.5 | E3: =C3-D3 -> 219 | F3: =YEAR(Ventas!G3) -> 2016 | G3: =MONTH(Ventas!G3) -> 7 | H3: =VLOOKUP(Ventas!C3,Países!$A$2:$B$186,2,FALSE) -> Central America and the Caribbean | I3: =Ventas!E3 -> Online
B4: =Ventas!F4 -> 205 | C4: =VLOOKUP(Ventas!$D4,Productos!$A$1:$D$16,4,FALSE)*Ventas!F4 -> 1845 | D4: =VLOOKUP(Ventas!$D4,Productos!$A$1:$D$16,3,FALSE)*Ventas!F4 -> 1230 | E4: =C4-D4 -> 615 | F4: =YEAR(Ventas!G4) -> 2016 | G4: =MONTH(Ventas!G4) -> 8 | H4: =VLOOKUP(Ventas!C4,Países!$A$2:$B$186,2,FALSE) -> Sub-Saharan Africa | I4: =Ventas!E4 -> Retail
B5: =Ventas!F5 -> 14 | C5: =VLOOKUP(Ventas!$D5,Productos!$A$1:$D$16,4,FALSE)*Ventas!F5 -> 139.86 | D5: =VLOOKUP(Ventas!$D5,Productos!$A$1:$D$16,3,FALSE)*Ventas!F5 -> 70 | E5: =C5-D5 -> 69.86 | F5: =YEAR(Ventas!G5) -> 2016 | G5: =MONTH(Ventas!G5) -> 8 | H5: =VLOOKUP(Ventas!C5,Países!$A$2:$B$186,2,FALSE) -> Sub-Saharan Africa | I5: =Ventas!E5 -> Retail
B6: =Ventas!F6 -> 170 | C6: =VLOOKUP(Ventas!$D6,Productos!$A$1:$D$16,4,FALSE)*Ventas!F6 -> 678.3 | D6: =VLOOKUP(Ventas!$D6,Productos!$A$1:$D$16,3,FALSE)*Ventas!F6 -> 340 | E6: =C6-D6 -> 338.3 | F6: =YEAR(Ventas!G6) -> 2016 | G6: =MONTH(Ventas!G6) -> 8 | H6: =VLOOKUP(Ventas!C6,Países!$A$2:$B$186,2,FALSE) -> Sub-Saharan Africa | I6: =Ventas!E6 -> Retail
B7: =Ventas!F7 -> 129 | C7: =VLOOKUP(Ventas!$D7,Productos!$A$1:$D$16,4,FALSE)*Ventas!F7 -> 387 | D7: =VLOOKUP(Ventas!$D7,Productos!$A$1:$D$16,3,FALSE)*Ventas!F7 -> 193.5 | E7: =C7-D7 -> 193.5 | F7: =YEAR(Ventas!G7) -> 2016 | G7: =MONTH(Ventas!G7) -> 7 | H7: =VLOOKUP(Ventas!C7,Países!$A$2:$B$186,2,FALSE) -> Middle East and North Africa | I7: =Ventas!E7 -> Retail
B8: =Ventas!F8 -> 82 | C8: =VLOOKUP(Ventas!$D8,Productos!$A$1:$D$16,4,FALSE)*Ventas!F8 -> 492 | D8: =VLOOKUP(Ventas!$D8,Productos!$A$1:$D$16,3,FALSE)*Ventas!F8 -> 246 | E8: =C8-D8 -> 246 | F8: =YEAR(Ventas!G8) -> 2016 | G8: =MONTH(Ventas!G8) -> 7 | H8: =VLOOKUP(Ventas!C8,Países!$A$2:$B$186,2,FALSE) -> Central America and the Caribbean | I8: =Ventas!E8 -> Online
B9: =Ventas!F9 -> 116 | C9: =VLOOKUP(Ventas!$D9,Productos!$A$1:$D$16,4,FALSE)*Ventas!F9 -> 348 | D9: =VLOOKUP(Ventas!$D9,Productos!$A$1:$D$16,3,FALSE)*Ventas!F9 -> 174 | E9: =C9-D9 -> 174 | F9: =YEAR(Ventas!G9) -> 2016 | G9: =MONTH(Ventas!G9) -> 6 | H9: =VLOOKUP(Ventas!C9,Países!$A$2:$B$186,2,FALSE) -> Europe | I9: =Ventas!E9 -> Retail
B10: =Ventas!F10 -> 67 | C10: =VLOOKUP(Ventas!$D10,Productos!$A$1:$D$16,4,FALSE)*Ventas!F10 -> 468.33 | D10: =VLOOKUP(Ventas!$D10,Productos!$A$1:$D$16,3,FALSE)*Ventas!F10 -> 234.5 | E10: =C10-D10 -> 233.83 | F10: =YEAR(Ventas!G10) -> 2016 | G10: =MONTH(Ventas!G10) -> 6 | H10: =VLOOKUP(Ventas!C10,Países!$A$2:$B$186,2,FALSE) -> Asia | I10: =Ventas!E10 -> Online
B11: =Ventas!F11 -> 125 | C11: =VLOOKUP(Ventas!$D11,Productos!$A$1:$D$16,4,FALSE)*Ventas!F11 -> 873.75 | D11: =VLOOKUP(Ventas!$D11,Productos!$A$1:$D$16,3,FALSE)*Ventas!F11 -> 437.5 | E11: =C11-D11 -> 436.25 | F11: =YEAR(Ventas!G11) -> 2016 | G11: =MONTH(Ventas!G11) -> 7 | H11: =VLOOKUP(Ventas!C11,Países!$A$2:$B$186,2,FALSE) -> Sub-Saharan Africa | I11: =Ventas!E11 -> Retail
B12: =Ventas!F12 -> 71 | C12: =VLOOKUP(Ventas!$D12,Productos!$A$1:$D$16,4,FALSE)*Ventas!F12 -> 461.5 | D12: =VLOOKUP(Ventas!$D12,Productos!$A$1:$D$16,3,FALSE)*Ventas!F12 -> 248.5 | E12: =C12-D12 -> 213 | F12: =YEAR(Ventas!G12) -> 2016 | G12: =MONTH(Ventas!G12) -> 7 | H12: =VLOOKUP(Ventas!C12,Países!$A$2:$B$186,2,FALSE) -> Asia | I12: =Ventas!E12 -> Retail
B13: =Ventas!F13 -> 22 | C13: =VLOOKUP(Ventas!$D13,Productos!$A$1:$D$16,4,FALSE)*Ventas!F13 -> 219.78 | D13: =VLOOKUP(Ventas!$D13,Productos!$A$1:$D$16,3,FALSE)*Ventas!F13 -> 110 | E13: =C13-D13 -> 109.78 | F13: =YEAR(Ventas!G13) -> 2016 | G13: =MONTH(Ventas!G13) -> 8 | H13: =VLOOKUP(Ventas!C13,Países!$A$2:$B$186,2,FALSE) -> Europe | I13: =Ventas!E13 -> Online
... B999: =Ventas!F999 -> 138 | C999: =VLOOKUP(Ventas!$D999,Productos!$A$1:$D$16,4,FALSE)*Ventas!F999 -> 897 | D999: =VLOOKUP(Ventas!$D999,Productos!$A$1:$D$16,3,FALSE)*Ventas!F999 -> 483 | E999: =C999-D999 -> 414 | F999: =YEAR(Ventas!G999) -> 2015 | G999: =MONTH(Ventas!G999) -> 8 | H999: =VLOOKUP(Ventas!C999,Países!$A$2:$B$186,2,FALSE) -> Asia | I999: =Ventas!E999 -> Online

Sheet TablaCompleta
A1: IdCliente | B1: NombreCliente | C1: Pais | D1: Region | E1: IdProducto | F1: productName | G1: CosteStandard | H1: PrecioStandard | I1: CanalVentas | J1: UdsVendidas | K1: FechaVenta
A2: 23262 | B2: CESAR VARGAS | C2: Comoros | D2: =VLOOKUP(C2,Países!$A$1:$B$186,2,TRUE) -> Sub-Saharan Africa | E2: C1 | F2: =VLOOKUP(E2,Productos!$A$2:$D$13,2,TRUE) -> garrafa 1l | G2: =VLOOKUP(E2,Productos!$A$2:$D$13,3,TRUE) -> 1 | H2: =VLOOKUP(E2,Productos!$A$2:$D$13,4,TRUE) -> 2 | I2: Online | J2: 117 | K2: 42591
A3: 23263 | B3: CARLA CABALLERO | C3: Panama | D3: =VLOOKUP(C3,Países!$A$1:$B$186,2,TRUE) -> Central America and the Caribbean | E3: B2 | F3: =VLOOKUP(E3,Productos!$A$2:$D$13,2,TRUE) -> botella 1l | G3: =VLOOKUP(E3,Productos!$A$2:$D$13,3,TRUE) -> 3.5 | H3: =VLOOKUP(E3,Productos!$A$2:$D$13,4,TRUE) -> 6.5 | I3: Online | J3: 73 | K3: 42557
A4: 23264 | B4: MATEO SANCHEZ | C4: Tanzania | D4: =VLOOKUP(C4,Países!$A$1:$B$186,2,TRUE) -> Sub-Saharan Africa | E4: B3 | F4: =VLOOKUP(E4,Productos!$A$2:$D$13,2,TRUE) -> botella 5l | G4: =VLOOKUP(E4,Productos!$A$2:$D$13,3,TRUE) -> 6 | H4: =VLOOKUP(E4,Productos!$A$2:$D$13,4,TRUE) -> 9 | I4: Retail | J4: 205 | K4: 42600
A5: 23265 | B5: ADRIAN GIL | C5: South Africa | D5: =VLOOKUP(C5,Países!$A$1:$B$186,2,TRUE) -> Sub-Saharan Africa | E5: C4 | F5: =VLOOKUP(E5,Productos!$A$2:$D$13,2,TRUE) -> garrafa 4l | G5: =VLOOKUP(E5,Productos!$A$2:$D$13,3,TRUE) -> 5 | H5: =VLOOKUP(E5,Productos!$A$2:$D$13,4,TRUE) -> 9.99 | I5: Retail | J5: 14 | K5: 42587
A6: 23266 | B6: CAROLINA FRANCO | C6: Gabon | D6: =VLOOKUP(C6,Países!$A$1:$B$186,2,TRUE) -> Sub-Saharan Africa | E6: A2 | F6: =VLOOKUP(E6,Productos!$A$2:$D$13,2,TRUE) -> botellín 400cc | G6: =VLOOKUP(E6,Productos!$A$2:$D$13,3,TRUE) -> 2.3 | H6: =VLOOKUP(E6,Productos!$A$2:$D$13,4,TRUE) -> 4.5 | I6: Retail | J6: 170 | K6: 42593
A7: 23267 | B7: RAUL AVILA | C7: Syria | D7: =VLOOKUP(C7,Países!$A$1:$B$186,2,TRUE) -> Middle East and North Africa | E7: A1 | F7: =VLOOKUP(E7,Productos!$A$2:$D$13,2,TRUE) -> botellín 200cc | G7: =VLOOKUP(E7,Productos!$A$2:$D$13,3,TRUE) -> 1.5 | H7: =VLOOKUP(E7,Productos!$A$2:$D$13,4,TRUE) -> 3 | I7: Retail | J7: 129 | K7: 42562
A8: 23268 | B8: ENRIQUE PEREIRA | C8: Grenada | D8: =VLOOKUP(C8,Países!$A$1:$B$186,2,TRUE) -> Central America and the Caribbean | E8: B1 | F8: =VLOOKUP(E8,Productos!$A$2:$D$13,2,TRUE) -> botella 0.5l | G8: =VLOOKUP(E8,Productos!$A$2:$D$13,3,TRUE) -> 3 | H8: =VLOOKUP(E8,Productos!$A$2:$D$13,4,TRUE) -> 6 | I8: Online | J8: 82 | K8: 42563
A9: 23269 | B9: ALBERTO LUQUE | C9: Macedonia | D9: =VLOOKUP(C9,Países!$A$1:$B$186,2,TRUE) -> Europe | E9: A1 | F9: =VLOOKUP(E9,Productos!$A$2:$D$13,2,TRUE) -> botellín 200cc | G9: =VLOOKUP(E9,Productos!$A$2:$D$13,3,TRUE) -> 1.5 | H9: =VLOOKUP(E9,Productos!$A$2:$D$13,4,TRUE) -> 3 | I9: Retail | J9: 116 | K9: 42524
A10: 23270 | B10: ALBERTO MORALES | C10: Kyrgyzstan | D10: =VLOOKUP(C10,Países!$A$1:$B$186,2,TRUE) -> Asia | E10: C3 | F10: =VLOOKUP(E10,Productos!$A$2:$D$13,2,TRUE) -> garrafa 3l | G10: =VLOOKUP(E10,Productos!$A$2:$D$13,3,TRUE) -> 3.5 | H10: =VLOOKUP(E10,Productos!$A$2:$D$13,4,TRUE) -> 6.99 | I10: Online | J10: 67 | K10: 42528
A11: 23271 | B11: ADRIAN MARTINEZ | C11: Republic of the Congo | D11: =VLOOKUP(C11,Países!$A$1:$B$186,2,TRUE) -> Sub-Saharan Africa | E11: C3 | F11: =VLOOKUP(E11,Productos!$A$2:$D$13,2,TRUE) -> garrafa 3l | G11: =VLOOKUP(E11,Productos!$A$2:$D$13,3,TRUE) -> 3.5 | H11: =VLOOKUP(E11,Productos!$A$2:$D$13,4,TRUE) -> 6.99 | I11: Retail | J11: 125 | K11: 42578
A12: 23272 | B12: INES MARTINEZ | C12: Turkmenistan | D12: =VLOOKUP(C12,Países!$A$1:$B$186,2,TRUE) -> Asia | E12: B2 | F12: =VLOOKUP(E12,Productos!$A$2:$D$13,2,TRUE) -> botella 1l | G12: =VLOOKUP(E12,Productos!$A$2:$D$13,3,TRUE) -> 3.5 | H12: =VLOOKUP(E12,Productos!$A$2:$D$13,4,TRUE) -> 6.5 | I12: Retail | J12: 71 | K12: 42582
A13: 23273 | B13: JUDITH RODRIGUEZ | C13: Netherlands | D13: =VLOOKUP(C13,Países!$A$1:$B$186,2,TRUE) -> Europe | E13: C4 | F13: =VLOOKUP(E13,Productos!$A$2:$D$13,2,TRUE) -> garrafa 4l | G13: =VLOOKUP(E13,Productos!$A$2:$D$13,3,TRUE) -> 5 | H13: =VLOOKUP(E13,Productos!$A$2:$D$13,4,TRUE) -> 9.99 | I13: Online | J13: 22 | K13: 42595
... A999: 24259 | B999: PAOLA RAMIREZ | C999: China | D999: =VLOOKUP(C999,Países!$A$1:$B$186,2,TRUE) -> Asia | E999: A4 | F999: =VLOOKUP(E999,Productos!$A$2:$D$13,2,TRUE) -> botellín 500cc | G999: =VLOOKUP(E999,Productos!$A$2:$D$13,3,TRUE) -> 3.5 | H999: =VLOOKUP(E999,Productos!$A$2:$D$13,4,TRUE) -> 6.5 | I999: Online | J999: 138 | K999: 42225

Sheet Escenarios
F1: AÑO | G1: (Todas)
F3: REGIÓN | G3: Suma de UdsVendidas | H3: Suma de COSTES | I3: Suma de INGRESOS | J3: Suma de BENEFICIOS | K3: Estimación | L3: Estimación Unidades Vendidas | M3: Estimación Costes | N3: Estimación Ingresos | O3: Estimación Beneficios
F4: Asia | G4: 14664 | H4: 50661 | I4: 94131.51 | J4: 43470.51 | K4: 0.04 | L4: =G4*(1+K4) -> 15250.56 | M4: =H4*(1+$K4) -> 52687.44 | N4: =I4*(1+$K4) -> 97896.77 | O4: =J4*(1+$K4) -> 45209.33
F5: Australia and Oceania | G5: 9101 | H5: 28672.5 | I5: 53471.88 | J5: 24799.38 | K5: 0.01 | L5: =G5*(1+K5) -> 9192.01 | M5: =H5*(1+$K5) -> 28959.225 | N5: =I5*(1+$K5) -> 54006.599 | O5: =J5*(1+$K5) -> 25047.374
F6: Central America and the Caribbean | G6: 10981 | H6: 31760.5 | I6: 59874.98 | J6: 28114.48 | K6: 0.02 | L6: =G6*(1+K6) -> 11200.62 | M6: =H6*(1+$K6) -> 32395.71 | N6: =I6*(1+$K6) -> 61072.48 | O6: =J6*(1+$K6) -> 28676.77
F7: Europe | G7: 26929 | H7: 87112.5 | I7: 163060.4 | J7: 75947.9 | K7: -0.02 | L7: =G7*(1+K7) -> 26390.42 | M7: =H7*(1+$K7) -> 85370.25 | N7: =I7*(1+$K7) -> 159799.19 | O7: =J7*(1+$K7) -> 74428.942
F8: Middle East and North Africa | G8: 13689 | H8: 45325 | I8: 83814.86 | J8: 38489.86 | K8: -0.01 | L8: =G8*(1+K8) -> 13552.11 | M8: =H8*(1+$K8) -> 44871.75 | N8: =I8*(1+$K8) -> 82976.711 | O8: =J8*(1+$K8) -> 38104.961
F9: North America | G9: 1028 | H9: 4488.5 | I9: 8247.9 | J9: 3759.4 | K9: 0.02 | L9: =G9*(1+K9) -> 1048.56 | M9: =H9*(1+$K9) -> 4578.27 | N9: =I9*(1+$K9) -> 8412.858 | O9: =J9*(1+$K9) -> 3834.588
F10: Sub-Saharan Africa | G10: 31648 | H10: 108910.5 | I10: 199821.18 | J10: 90910.68 | K10: -0.03 | L10: =G10*(1+K10) -> 30698.56 | M10: =H10*(1+$K10) -> 105643.18 | N10: =I10*(1+$K10) -> 193826.54 | O10: =J10*(1+$K10) -> 88183.36
F11: Total general | G11: 108040 | H11: 356930.5 | I11: 662422.71 | J11: 305492.21 | L11: =SUM(L4:L10) -> 107332.84 | M11: =SUM(M4:M10) -> 354505.83 | N11: =SUM(N4:N10) -> 657991.15 | O11: =SUM(O4:O10) -> 303485.32

Sheet Gráficos
B1: INGRESOS TOTALES POR REGIÓN Y CANAL DE VENTAS | C1: CANAL DE VENTAS
B2: REGIÓN | C2: Direct | D2: Online | E2: Retail | F2: Total general
B3: Asia | C3: 12571.47 | D3: 47648.41 | E3: 33911.63 | F3: 94131.51
B4: Australia and Oceania | C4: 4909.78 | D4: 27444.92 | E4: 21117.18 | F4: 53471.88
B5: Central America and the Caribbean | C5: 3258.07 | D5: 33951.42 | E5: 22665.49 | F5: 59874.98
B6: Europe | C6: 24247.63 | D6: 66313.44 | E6: 72499.33 | F6: 163060.4
B7: Middle East and North Africa | C7: 5907.58 | D7: 38810.47 | E7: 39096.81 | F7: 83814.86
B8: North America | D8: 4227.72 | E8: 4020.18 | F8: 8247.9
B9: Sub-Saharan Africa | C9: 16043.37 | D9: 93356.24 | E9: 90421.57 | F9: 199821.18
B10: Total general | C10: 66937.9 | D10: 311752.62 | E10: 283732.19 | F10: 662422.71
B31: COSTES TOTALES POR REGIÓN Y CANAL DE VENTAS | C31: CANAL DE VENTAS
B32: REGIÓN | C32: Direct | D32: Online | E32: Retail | F32: Total general
B33: Asia | C33: 6774.5 | D33: 25880.5 | E33: 18006 | F33: 50661
B34: Australia and Oceania | C34: 2796.5 | D34: 14312.5 | E34: 11563.5 | F34: 28672.5
B35: Central America and the Caribbean | C35: 1795.5 | D35: 18040.5 | E35: 11924.5 | F35: 31760.5
B36: Europe | C36: 12621.5 | D36: 35505 | E36: 38986 | F36: 87112.5
B37: Middle East and North Africa | C37: 3222 | D37: 20786 | E37: 21317 | F37: 45325
B38: North America | D38: 2333.5 | E38: 2155 | F38: 4488.5
B39: Sub-Saharan Africa | C39: 8519 | D39: 50635.5 | E39: 49756 | F39: 108910.5
B40: Total general | C40: 35729 | D40: 167493.5 | E40: 153708 | F40: 356930.5
B61: BENEFICIOS TOTALES POR REGIÓN Y CANAL DE VENTAS | C61: CANAL DE VENTAS
B62: REGIÓN | C62: Direct | D62: Online | E62: Retail | F62: Total general
B63: Asia | C63: 5796.97 | D63: 21767.91 | E63: 15905.63 | F63: 43470.51
B64: Australia and Oceania | C64: 2113.28 | D64: 13132.42 | E64: 9553.68 | F64: 24799.38
B65: Central America and the Caribbean | C65: 1462.57 | D65: 15910.92 | E65: 10740.99 | F65: 28114.48
B66: Europe | C66: 11626.13 | D66: 30808.44 | E66: 33513.33 | F66: 75947.9
B67: Middle East and North Africa | C67: 2685.58 | D67: 18024.47 | E67: 17779.81 | F67: 38489.86
B68: North America | D68: 1894.22 | E68: 1865.18 | F68: 3759.4
B69: Sub-Saharan Africa | C69: 7524.37 | D69: 42720.74 | E69: 40665.57 | F69: 90910.68
B70: Total general | C70: 31208.9 | D70: 144259.12 | E70: 130024.19 | F70: 305492.21
B91: UNIDADES VENDIDAS TOTALES POR REGIÓN Y CANAL DE VENTAS | C91: CANAL DE VENTAS
B92: REGIÓN | C92: Direct | D92: Online | E92: Retail | F92: Total general
B93: Asia | C93: 1588 | D93: 7212 | E93: 5864 | F93: 14664
B94: Australia and Oceania | C94: 848 | D94: 5112 | E94: 3141 | F94: 9101
B95: Central America and the Caribbean | C95: 740 | D95: 5913 | E95: 4328 | F95: 10981
B96: Europe | C96: 3588 | D96: 11805 | E96: 11536 | F96: 26929
B97: Middle East and North Africa | C97: 1014 | D97: 6707 | E97: 5968 | F97: 13689
B98: North America | D98: 573 | E98: 455 | F98: 1028
B99: Sub-Saharan Africa | C99: 2985 | D99: 15335 | E99: 13328 | F99: 31648
B100: Total general | C100: 10763 | D100: 52657 | E100: 44620 | F100: 108040

Sheet Rentabilidad
A1: AÑO | B1: 2015
A3: REGIÓN | B3: Suma de UdsVendidas | C3: Suma de COSTES | D3: Suma de INGRESOS | E3: Suma de BENEFICIOS | F3: Inventario | G3: Rotación | H3: Margen | I3: Rentabilidad
A4: Asia | B4: 6643 | C4: 19625 | D4: 37033.45 | E4: 17408.45 | F4: =Inventarios!B3 -> 10972 | G4: =C4/F4 -> 1.7886438 | H4: =(D4-C4)/C4 -> 0.88705478 | I4: =H4*G4 -> 1.586625
A5: Australia and Oceania | B5: 3144 | C5: 9022 | D5: 17018.58 | E5: 7996.58 | F5: =Inventarios!B4 -> 4047 | G5: =C5/F5 -> 2.2293057 | H5: =(D5-C5)/C5 -> 0.88634227 | I5: =H5*G5 -> 1.9759278
A6: Central America and the Caribbean | B6: 3910 | C6: 11037.5 | D6: 21013.33 | E6: 9975.83 | F6: =Inventarios!B5 -> 7690 | G6: =C6/F6 -> 1.4353056 | H6: =(D6-C6)/C6 -> 0.90381246 | I6: =H6*G6 -> 1.2972471
A7: Europe | B7: 10432 | C7: 30254 | D7: 56872.48 | E7: 26618.48 | F7: =Inventarios!B6 -> 12372 | G7: =C7/F7 -> 2.4453605 | H7: =(D7-C7)/C7 -> 0.87983341 | I7: =H7*G7 -> 2.1515099
A8: Middle East and North Africa | B8: 6182 | C8: 19765.5 | D8: 36690.79 | E8: 16925.29 | F8: =Inventarios!B7 -> 11415 | G8: =C8/F8 -> 1.7315375 | H8: =(D8-C8)/C8 -> 0.85630467 | I8: =H8*G8 -> 1.4827236
A9: North America | B9: 209 | C9: 476.5 | D9: 947.97 | E9: 471.47 | F9: =Inventarios!B8 -> 285 | G9: =C9/F9 -> 1.6719298 | H9: =(D9-C9)/C9 -> 0.98944386 | I9: =H9*G9 -> 1.6542807
A10: Sub-Saharan Africa | B10: 11849 | C10: 43322 | D10: 78578.84 | E10: 35256.84 | F10: =Inventarios!B9 -> 26618 | G10: =C10/F10 -> 1.6275453 | H10: =(D10-C10)/C10 -> 0.81383223 | I10: =H10*G10 -> 1.3245488
A11: Total general | B11: 42369 | C11: 133502.5 | D11: 248155.44 | E11: 114652.94 | F11: =SUM(F4:F10) -> 73399 | G11: =AVERAGE(G4:G10) -> 1.8470897 | H11: =AVERAGE(H4:H10) -> 0.8880891 | I11: =AVERAGE(I4:I10) -> 1.6389804
C14: ROI | D14: ROI OBJETIVO | E14: VALOR INVENTARIO MEDIO
C15: =E11/F11 -> 1.5620504 | D15: =IFERROR(E11/$E$15,0) -> 3.9999994 | E15: 28663.239
A18: AÑO | B18: 2016
A20: REGIÓN | B20: Suma de COSTES | C20: Suma de UdsVendidas | D20: Suma de INGRESOS | E20: Suma de BENEFICIOS | F20: Inventario | G20: Rotación | H20: Margen | I20: Rentabilidad
A21: Asia | B21: 31036 | C21: 8021 | D21: 57098.06 | E21: 26062.06 | F21: =Inventarios!C3 -> 18721 | G21: =B21/F21 -> 1.6578174 | H21: =(D21-B21)/B21 -> 0.83973644 | I21: =H21*G21 -> 1.3921297
A22: Australia and Oceania | B22: 19650.5 | C22: 5957 | D22: 36453.3 | E22: 16802.8 | F22: =Inventarios!C4 -> 9654 | G22: =B22/F22 -> 2.0354775 | H22: =(D22-B22)/B22 -> 0.85508257 | I22: =H22*G22 -> 1.7405013
A23: Central America and the Caribbean | B23: 20723 | C23: 7071 | D23: 38861.65 | E23: 18138.65 | F23: =Inventarios!C5 -> 14672 | G23: =B23/F23 -> 1.4124182 | H23: =(D23-B23)/B23 -> 0.87529074 | I23: =H23*G23 -> 1.2362766
A24: Europe | B24: 56858.5 | C24: 16497 | D24: 106187.92 | E24: 49329.42 | F24: =Inventarios!C6 -> 22716 | G24: =B24/F24 -> 2.5030155 | H24: =(D24-B24)/B24 -> 0.86758216 | I24: =H24*G24 -> 2.1715716
A25: Middle East and North Africa | B25: 25559.5 | C25: 7507 | D25: 47124.07 | E25: 21564.57 | F25: =Inventarios!C7 -> 15102 | G25: =B25/F25 -> 1.692458 | H25: =(D25-B25)/B25 -> 0.84370078 | I25: =H25*G25 -> 1.4279281
A26: North America | B26: 4012 | C26: 819 | D26: 7299.93 | E26: 3287.93 | F26: =Inventarios!C8 -> 1429 | G26: =B26/F26 -> 2.8075577 | H26: =(D26-B26)/B26 -> 0.81952393 | I26: =H26*G26 -> 2.3008607
A27: Sub-Saharan Africa | B27: 65588.5 | C27: 19799 | D27: 121242.34 | E27: 55653.84 | F27: =Inventarios!C9 -> 39447 | G27: =B27/F27 -> 1.6626993 | H27: =(D27-B27)/B27 -> 0.84853046 | I27: =H27*G27 -> 1.410851
A28: Total general | B28: 223428 | C28: 65671 | D28: 414267.27 | E28: 190839.27 | F28: =SUM(F21:F27) -> 121741 | G28: =AVERAGE(G21:G27) -> 1.9673491 | H28: =AVERAGE(H21:H27) -> 0.84992101 | I28: =AVERAGE(I21:I27) -> 1.6685884
C32: ROI | D32: ROI OBJETIVO | E32: VALOR INVENTARIO MEDIO
C33: =E28/F28 -> 1.5675842 | D33: =IFERROR(E28/E33,0) -> 4 | E33: 47709.818
